odoo8_addon_l10n_es_aeat_vat_prorrate-8.0.2.0.2-py2.7-nspkg.pth
odoo8_addon_l10n_es_aeat_vat_prorrate-8.0.2.0.2.dist-info/DESCRIPTION.rst
odoo8_addon_l10n_es_aeat_vat_prorrate-8.0.2.0.2.dist-info/METADATA
odoo8_addon_l10n_es_aeat_vat_prorrate-8.0.2.0.2.dist-info/RECORD
odoo8_addon_l10n_es_aeat_vat_prorrate-8.0.2.0.2.dist-info/WHEEL
odoo8_addon_l10n_es_aeat_vat_prorrate-8.0.2.0.2.dist-info/metadata.json
odoo8_addon_l10n_es_aeat_vat_prorrate-8.0.2.0.2.dist-info/namespace_packages.txt
odoo8_addon_l10n_es_aeat_vat_prorrate-8.0.2.0.2.dist-info/top_level.txt
odoo_addons/l10n_es_aeat_vat_prorrate/README.rst
odoo_addons/l10n_es_aeat_vat_prorrate/__init__.py
odoo_addons/l10n_es_aeat_vat_prorrate/__openerp__.py
odoo_addons/l10n_es_aeat_vat_prorrate/data/aeat_export_mod303_data.xml
odoo_addons/l10n_es_aeat_vat_prorrate/data/tax_code_map_mod303_data.xml
odoo_addons/l10n_es_aeat_vat_prorrate/i18n/bg.po
odoo_addons/l10n_es_aeat_vat_prorrate/i18n/ca.po
odoo_addons/l10n_es_aeat_vat_prorrate/i18n/ca_ES.po
odoo_addons/l10n_es_aeat_vat_prorrate/i18n/cs.po
odoo_addons/l10n_es_aeat_vat_prorrate/i18n/es.po
odoo_addons/l10n_es_aeat_vat_prorrate/i18n/es_CO.po
odoo_addons/l10n_es_aeat_vat_prorrate/i18n/es_CR.po
odoo_addons/l10n_es_aeat_vat_prorrate/i18n/eu.po
odoo_addons/l10n_es_aeat_vat_prorrate/i18n/fr.po
odoo_addons/l10n_es_aeat_vat_prorrate/i18n/gl.po
odoo_addons/l10n_es_aeat_vat_prorrate/i18n/hr.po
odoo_addons/l10n_es_aeat_vat_prorrate/i18n/nl.po
odoo_addons/l10n_es_aeat_vat_prorrate/i18n/pl.po
odoo_addons/l10n_es_aeat_vat_prorrate/i18n/pt.po
odoo_addons/l10n_es_aeat_vat_prorrate/i18n/pt_BR.po
odoo_addons/l10n_es_aeat_vat_prorrate/i18n/ru.po
odoo_addons/l10n_es_aeat_vat_prorrate/i18n/sl.po
odoo_addons/l10n_es_aeat_vat_prorrate/i18n/sv.po
odoo_addons/l10n_es_aeat_vat_prorrate/i18n/tr.po
odoo_addons/l10n_es_aeat_vat_prorrate/i18n/vi.po
odoo_addons/l10n_es_aeat_vat_prorrate/models/__init__.py
odoo_addons/l10n_es_aeat_vat_prorrate/models/mod303.py
odoo_addons/l10n_es_aeat_vat_prorrate/static/description/icon.png
odoo_addons/l10n_es_aeat_vat_prorrate/static/description/icon_source.svg
odoo_addons/l10n_es_aeat_vat_prorrate/tests/__init__.py
odoo_addons/l10n_es_aeat_vat_prorrate/tests/test_l10n_es_vat_prorrate.py
odoo_addons/l10n_es_aeat_vat_prorrate/views/mod303_view.xml
odoo_addons/l10n_es_aeat_vat_prorrate/wizard/__init__.py
odoo_addons/l10n_es_aeat_vat_prorrate/wizard/l10n_es_aeat_compute_vat_prorrate.py
